cmk_dev_site/__init__.py
cmk_dev_site/cmk_dev_install.py
cmk_dev_site/cmk_dev_install_site.py
cmk_dev_site/cmk_dev_site.py
cmk_dev_site/version.py
cmk_dev_site/cmk/__init__.py
cmk_dev_site/cmk/rest_api.py
cmk_dev_site/omd/__init__.py
cmk_dev_site/saas/__init__.py
cmk_dev_site/saas/config.py
cmk_dev_site/saas/constants.py
cmk_dev_site/saas/oidc_service.py
cmk_dev_site/utils/__init__.py
cmk_dev_site/utils/log.py
cmk_dev_site-1.11.1.dist-info/METADATA
cmk_dev_site-1.11.1.dist-info/WHEEL
cmk_dev_site-1.11.1.dist-info/entry_points.txt
cmk_dev_site-1.11.1.dist-info/licenses/LICENSE
cmk_dev_site-1.11.1.dist-info/RECORD
