Metadata-Version: 2.4
Name: cmk-dev-site
Version: 1.11.1
Summary: Easily Install Checkmk
Project-URL: Repository, https://github.com/Checkmk/cmk-dev-site
Project-URL: Changelog, https://github.com/Checkmk/cmk-dev-site/blob/release/1.11.1/changelog.md
License-Expression: GPL-3.0-only
License-File: LICENSE
Keywords: checkmk,cmk,monitoring,site
Classifier: Development Status :: 4 - Beta
Classifier: Intended Audience :: Developers
Classifier: License :: OSI Approved :: GNU General Public License v3 (GPLv3)
Classifier: Operating System :: Unix
Classifier: Programming Language :: Python :: 3
Classifier: Topic :: Software Development
Classifier: Topic :: Software Development :: Build Tools
Requires-Python: <4.0,>=3.11
Requires-Dist: checkmk-dev-tools<1,>=0.10.1
Requires-Dist: fastapi
Requires-Dist: pyjwt[crypto]
Requires-Dist: python-multipart>=0.0.20
Requires-Dist: requests
Requires-Dist: uvicorn
